aau_ais_utilities-0.1.19.dist-info/METADATA
aau_ais_utilities-0.1.19.dist-info/WHEEL
aau_ais_utilities/__init__.py
aau_ais_utilities/connections/__init__.py
aau_ais_utilities/connections/engine_settings.py
aau_ais_utilities/connections/postgresql_connection.py
aau_ais_utilities/lookup/__init__.py
aau_ais_utilities/lookup/mmsi.py
aau_ais_utilities/validate/__init__.py
aau_ais_utilities/validate/imo.py
aau_ais_utilities/validate/mmsi.py
aau_ais_utilities/validate/validator.py
aau_ais_utilities-0.1.19.dist-info/RECORD
