Metadata-Version: 2.1
Name: aau-ais-utilities
Version: 0.1.19
Summary: Utilities for working with the AAU AIS database.
Author-Email: Mikael Vind Mikkelsen <mvmi@cs.aau.dk>
License: MIT
Requires-Python: ==3.12.*
Requires-Dist: sqlalchemy==2.0.*
Requires-Dist: pydantic-settings==2.2.*
